{
  "format": { "encoding": "pcm16", "sampleRate": 24000, "channels": 1 },
  "description": "Deterministic short PCM chunks used to test participant speech, Robin output, and barge-in without a Zoom account.",
  "turns": [
    { "speaker": "participant", "atMs": 0, "transcript": "Robin, prepare a short local note.", "pcmBase64": "AAAAAAAAAAAAAAAAAAAAAAAAAAAAAAAA" },
    { "speaker": "robin", "atMs": 900, "transcript": "I’ll prepare that now.", "pcmBase64": "AAAAAAAAAAAAAAAAAAAAAAAAAAAAAAAA" },
    { "speaker": "participant", "atMs": 1150, "event": "barge_in", "transcript": "Make the title Demo Result.", "pcmBase64": "AAAAAAAAAAAAAAAAAAAAAAAAAAAAAAAA" }
  ]
}
